{
  "id": "shiva-chalisa",
  "name": "दोहा",
  "nameEn": "जय गिरिजा पति दीन दयाला",
  "deity": "गिरिजा",
  "category": "god",
  "sourceUrl": "https://www.drikpanchang.com/lyrics/chalisa/lord-shiva/shiva-chalisa.html?lang=hi",
  "sourceName": "Drik Panchang",
  "sections": [
    {
      "id": "doha-opening",
      "title": "दोहा",
      "titleEn": "Doha",
      "verses": [
        {
          "lineHindi": "जय गणेश गिरिजा सुवन,मंगल मूल सुजान।",
          "lineEn": null
        },
        {
          "lineHindi": "कहत अयोध्यादास तुम,देहु अभय वरदान॥",
          "lineEn": null
        }
      ]
    },
    {
      "id": "chaupai",
      "title": "चौपाई",
      "titleEn": "Chaupai",
      "verses": [
        {
          "lineHindi": "जय गिरिजा पति दीन दयाला।सदा करत सन्तन प्रतिपाला॥",
          "lineEn": null
        },
        {
          "lineHindi": "भाल चन्द्रमा सोहत नीके।कानन कुण्डल नागफनी के॥",
          "lineEn": null
        },
        {
          "lineHindi": "अंग गौर शिर गंग बहाये।मुण्डमाल तन क्षार लगाए॥",
          "lineEn": null
        },
        {
          "lineHindi": "वस्त्र खाल बाघम्बर सोहे।छवि को देखि नाग मन मोहे॥",
          "lineEn": null
        },
        {
          "lineHindi": "मैना मातु की हवे दुलारी।बाम अंग सोहत छवि न्यारी॥",
          "lineEn": null
        },
        {
          "lineHindi": "कर त्रिशूल सोहत छवि भारी।करत सदा शत्रुन क्षयकारी॥",
          "lineEn": null
        },
        {
          "lineHindi": "नन्दि गणेश सोहै तहँ कैसे।सागर मध्य कमल हैं जैसे॥",
          "lineEn": null
        },
        {
          "lineHindi": "कार्तिक श्याम और गणराऊ।या छवि को कहि जात न काऊ॥",
          "lineEn": null
        },
        {
          "lineHindi": "देवन जबहीं जाय पुकारा।तब ही दुख प्रभु आप निवारा॥",
          "lineEn": null
        },
        {
          "lineHindi": "किया उपद्रव तारक भारी।देवन सब मिलि तुमहिं जुहारी॥",
          "lineEn": null
        },
        {
          "lineHindi": "तुरत षडानन आप पठायउ।लवनिमेष महँ मारि गिरायउ॥",
          "lineEn": null
        },
        {
          "lineHindi": "आप जलंधर असुर संहारा।सुयश तुम्हार विदित संसारा॥",
          "lineEn": null
        },
        {
          "lineHindi": "त्रिपुरासुर सन युद्ध मचाई।सबहिं कृपा कर लीन बचाई॥",
          "lineEn": null
        },
        {
          "lineHindi": "किया तपहिं भागीरथ भारी।पुरब प्रतिज्ञा तासु पुरारी॥",
          "lineEn": null
        },
        {
          "lineHindi": "दानिन महँ तुम सम कोउ नाहीं।सेवक स्तुति करत सदाहीं॥",
          "lineEn": null
        },
        {
          "lineHindi": "वेद माहि महिमा तुम गाई।अकथ अनादि भेद नहिं पाई॥",
          "lineEn": null
        },
        {
          "lineHindi": "प्रकटी उदधि मंथन में ज्वाला।जरत सुरासुर भए विहाला॥",
          "lineEn": null
        },
        {
          "lineHindi": "कीन्ही दया तहं करी सहाई।नीलकण्ठ तब नाम कहाई॥",
          "lineEn": null
        },
        {
          "lineHindi": "पूजन रामचन्द्र जब कीन्हा।जीत के लंक विभीषण दीन्हा॥",
          "lineEn": null
        },
        {
          "lineHindi": "सहस कमल में हो रहे धारी।कीन्ह परीक्षा तबहिं पुरारी॥",
          "lineEn": null
        },
        {
          "lineHindi": "एक कमल प्रभु राखेउ जोई।कमल नयन पूजन चहं सोई॥",
          "lineEn": null
        },
        {
          "lineHindi": "कठिन भक्ति देखी प्रभु शंकर।भए प्रसन्न दिए इच्छित वर॥",
          "lineEn": null
        },
        {
          "lineHindi": "जय जय जय अनन्त अविनाशी।करत कृपा सब के घटवासी॥",
          "lineEn": null
        },
        {
          "lineHindi": "दुष्ट सकल नित मोहि सतावै।भ्रमत रहौं मोहि चैन न आवै॥",
          "lineEn": null
        },
        {
          "lineHindi": "त्राहि त्राहि मैं नाथ पुकारो।येहि अवसर मोहि आन उबारो॥",
          "lineEn": null
        },
        {
          "lineHindi": "लै त्रिशूल शत्रुन को मारो।संकट ते मोहि आन उबारो॥",
          "lineEn": null
        },
        {
          "lineHindi": "मात-पिता भ्राता सब होई।संकट में पूछत नहिं कोई॥",
          "lineEn": null
        },
        {
          "lineHindi": "स्वामी एक है आस तुम्हारी।आय हरहु मम संकट भारी॥",
          "lineEn": null
        },
        {
          "lineHindi": "धन निर्धन को देत सदा हीं।जो कोई जांचे सो फल पाहीं॥",
          "lineEn": null
        },
        {
          "lineHindi": "अस्तुति केहि विधि करैं तुम्हारी।क्षमहु नाथ अब चूक हमारी॥",
          "lineEn": null
        },
        {
          "lineHindi": "शंकर हो संकट के नाशन।मंगल कारण विघ्न विनाशन॥",
          "lineEn": null
        },
        {
          "lineHindi": "योगी यति मुनि ध्यान लगावैं।शारद नारद शीश नवावैं॥",
          "lineEn": null
        },
        {
          "lineHindi": "नमो नमो जय नमः शिवाय।सुर ब्रह्मादिक पार न पाय॥",
          "lineEn": null
        },
        {
          "lineHindi": "जो यह पाठ करे मन लाई।ता पर होत है शम्भु सहाई॥",
          "lineEn": null
        },
        {
          "lineHindi": "ॠनियां जो कोई हो अधिकारी।पाठ करे सो पावन हारी॥",
          "lineEn": null
        },
        {
          "lineHindi": "पुत्र होन कर इच्छा जोई।निश्चय शिव प्रसाद तेहि होई॥",
          "lineEn": null
        },
        {
          "lineHindi": "पण्डित त्रयोदशी को लावे।ध्यान पूर्वक होम करावे॥",
          "lineEn": null
        },
        {
          "lineHindi": "त्रयोदशी व्रत करै हमेशा।ताके तन नहीं रहै कलेशा॥",
          "lineEn": null
        },
        {
          "lineHindi": "धूप दीप नैवेद्य चढ़ावे।शंकर सम्मुख पाठ सुनावे॥",
          "lineEn": null
        },
        {
          "lineHindi": "जन्म जन्म के पाप नसावे।अन्त धाम शिवपुर में पावे॥",
          "lineEn": null
        },
        {
          "lineHindi": "कहैं अयोध्यादास आस तुम्हारी।जानि सकल दुःख हरहु हमारी॥",
          "lineEn": null
        }
      ]
    },
    {
      "id": "doha-closing",
      "title": "दोहा",
      "titleEn": "Doha",
      "verses": [
        {
          "lineHindi": "नित्त नेम उठि प्रातः ही,पाठ करो चालीसा।",
          "lineEn": null
        },
        {
          "lineHindi": "तुम मेरी मनोकामना,पूर्ण करो जगदीश॥",
          "lineEn": null
        },
        {
          "lineHindi": "मगसिर छठि हेमन्त ॠतु,संवत चौसठ जान।",
          "lineEn": null
        },
        {
          "lineHindi": "स्तुति चालीसा शिवहि,पूर्ण कीन कल्याण॥",
          "lineEn": null
        }
      ]
    }
  ]
}