{
  "id": "shri-pitar-chalisa",
  "name": "दोहा",
  "nameEn": "पितरेश्वर करो मार्ग उजागर",
  "deity": "पितरेश्वर",
  "category": "god",
  "sourceUrl": "https://www.drikpanchang.com/lyrics/chalisa/shri-pitar/shri-pitar-chalisa.html?lang=hi",
  "sourceName": "Drik Panchang",
  "sections": [
    {
      "id": "doha-opening",
      "title": "दोहा",
      "titleEn": "Doha",
      "verses": [
        {
          "lineHindi": "हे पितरेश्वर आपको,दे दियो आशीर्वाद।",
          "lineEn": null
        },
        {
          "lineHindi": "चरणाशीश नवा दियो,रखदो सिर पर हाथ॥",
          "lineEn": null
        },
        {
          "lineHindi": "सबसे पहले गणपत,पाछे घर का देव मनावा जी।",
          "lineEn": null
        },
        {
          "lineHindi": "हे पितरेश्वर दया राखियो,करियो मन की चाया जी॥",
          "lineEn": null
        }
      ]
    },
    {
      "id": "chaupai",
      "title": "चौपाई",
      "titleEn": "Chaupai",
      "verses": [
        {
          "lineHindi": "पितरेश्वर करो मार्ग उजागर।चरण रज की मुक्ति सागर॥",
          "lineEn": null
        },
        {
          "lineHindi": "परम उपकार पित्तरेश्वर कीन्हा।मनुष्य योणि में जन्म दीन्हा॥",
          "lineEn": null
        },
        {
          "lineHindi": "मातृ-पितृ देव मनजो भावे।सोई अमित जीवन फल पावे॥",
          "lineEn": null
        },
        {
          "lineHindi": "जै-जै-जै पित्तर जी साईं।पितृ ऋण बिन मुक्ति नाहिं॥",
          "lineEn": null
        },
        {
          "lineHindi": "चारों ओर प्रताप तुम्हारा।संकट में तेरा ही सहारा॥",
          "lineEn": null
        },
        {
          "lineHindi": "नारायण आधार सृष्टि का।पित्तरजी अंश उसी दृष्टि का॥",
          "lineEn": null
        },
        {
          "lineHindi": "प्रथम पूजन प्रभु आज्ञा सुनाते।भाग्य द्वार आप ही खुलवाते॥",
          "lineEn": null
        },
        {
          "lineHindi": "झुंझुनू में दरबार है साजे।सब देवों संग आप विराजे॥",
          "lineEn": null
        },
        {
          "lineHindi": "प्रसन्न होय मनवांछित फल दीन्हा।कुपित होय बुद्धि हर लीन्हा॥",
          "lineEn": null
        },
        {
          "lineHindi": "पित्तर महिमा सबसे न्यारी।जिसका गुणगावे नर नारी॥",
          "lineEn": null
        },
        {
          "lineHindi": "तीन मण्ड में आप बिराजे।बसु रुद्र आदित्य में साजे॥",
          "lineEn": null
        },
        {
          "lineHindi": "नाथ सकल संपदा तुम्हारी।मैं सेवक समेत सुत नारी॥",
          "lineEn": null
        },
        {
          "lineHindi": "छप्पन भोग नहीं हैं भाते।शुद्ध जल से ही तृप्त हो जाते॥",
          "lineEn": null
        },
        {
          "lineHindi": "तुम्हारे भजन परम हितकारी।छोटे बड़े सभी अधिकारी॥",
          "lineEn": null
        },
        {
          "lineHindi": "भानु उदय संग आप पुजावै।पांच अँजुलि जल रिझावे॥",
          "lineEn": null
        },
        {
          "lineHindi": "ध्वज पताका मण्ड पे है साजे।अखण्ड ज्योति में आप विराजे॥",
          "lineEn": null
        },
        {
          "lineHindi": "सदियों पुरानी ज्योति तुम्हारी।धन्य हुई जन्म भूमि हमारी॥",
          "lineEn": null
        },
        {
          "lineHindi": "शहीद हमारे यहाँ पुजाते।मातृ भक्ति सन्देश सुनाते॥",
          "lineEn": null
        },
        {
          "lineHindi": "जगत पित्तरो सिद्धान्त हमारा।धर्म जाति का नहीं है नारा॥",
          "lineEn": null
        },
        {
          "lineHindi": "हिन्दु, मुस्लिम, सिख, ईसाई।सब पूजे पित्तर भाई॥",
          "lineEn": null
        },
        {
          "lineHindi": "हिन्दु वंश वृक्ष है हमारा।जान से ज्यादा हमको प्यारा॥",
          "lineEn": null
        },
        {
          "lineHindi": "गंगा ये मरुप्रदेश की।पितृ तर्पण अनिवार्य परिवेश की॥",
          "lineEn": null
        },
        {
          "lineHindi": "बन्धु छोड़ना इनके चरणाँ।इन्हीं की कृपा से मिले प्रभु शरणा॥",
          "lineEn": null
        },
        {
          "lineHindi": "चौदस को जागरण करवाते।अमावस को हम धोक लगाते॥",
          "lineEn": null
        },
        {
          "lineHindi": "श्री पित्तर जी भक्त हितकारी।सुन लीजे प्रभु अरज हमारी॥",
          "lineEn": null
        },
        {
          "lineHindi": "निशदिन ध्यान धरे जो कोई।ता सम भक्त और नहीं कोई॥",
          "lineEn": null
        },
        {
          "lineHindi": "तुम अनाथ के नाथ सहाई।दीनन के हो तुम सदा सहाई॥",
          "lineEn": null
        },
        {
          "lineHindi": "चारिक वेद प्रभु के साखी।तुम भक्तन की लज्जा राखी॥",
          "lineEn": null
        },
        {
          "lineHindi": "नाम तुम्हारो लेत जो कोई।ता सम धन्य और नहीं कोई॥",
          "lineEn": null
        },
        {
          "lineHindi": "जो तुम्हारे नित पाँव पलोटत।नवों सिद्धि चरणा में लोटत॥",
          "lineEn": null
        },
        {
          "lineHindi": "सिद्धि तुम्हारी सब मंगलकारी।जो तुम पे जावे बलिहारी॥",
          "lineEn": null
        },
        {
          "lineHindi": "जो तुम्हारे चरणा चित्त लावे।ताकी मुक्ति अवसी हो जावे॥",
          "lineEn": null
        },
        {
          "lineHindi": "सत्य भजन तुम्हारो जो गावे।सो निश्चय चारों फल पावे॥",
          "lineEn": null
        },
        {
          "lineHindi": "तुमहिं देव कुलदेव हमारे।तुम्हीं गुरुदेव प्राण से प्यारे॥",
          "lineEn": null
        },
        {
          "lineHindi": "सत्य आस मन में जो होई।मनवांछित फल पावें सोई॥",
          "lineEn": null
        },
        {
          "lineHindi": "तुम्हरी महिमा बुद्धि बड़ाई।शेष सहस्र मुख सके न गाई॥",
          "lineEn": null
        },
        {
          "lineHindi": "मैं अतिदीन मलीन दुखारी।करहु कौन विधि विनय तुम्हारी॥",
          "lineEn": null
        },
        {
          "lineHindi": "अब पित्तर जी दया दीन पर कीजै।अपनी भक्ति शक्ति कछु दीजै॥",
          "lineEn": null
        }
      ]
    },
    {
      "id": "doha-closing",
      "title": "दोहा",
      "titleEn": "Doha",
      "verses": [
        {
          "lineHindi": "पित्तरौं को स्थान दो,तीरथ और स्वयं ग्राम।",
          "lineEn": null
        },
        {
          "lineHindi": "श्रद्धा सुमन चढ़ें वहां,पूरण हो सब काम॥",
          "lineEn": null
        },
        {
          "lineHindi": "झुंझुनू धाम विराजे हैं,पित्तर हमारे महान।",
          "lineEn": null
        },
        {
          "lineHindi": "दर्शन से जीवन सफल हो,पूजे सकल जहान॥",
          "lineEn": null
        },
        {
          "lineHindi": "जीवन सफल जो चाहिए,चले झुंझुनू धाम।",
          "lineEn": null
        },
        {
          "lineHindi": "पित्तर चरण की धूल ले,हो जीवन सफल महान॥",
          "lineEn": null
        }
      ]
    }
  ]
}